LICENSE
README.md
setup.py
flask_pluginkit_accesscount/__init__.py
flask_pluginkit_accesscount.egg-info/PKG-INFO
flask_pluginkit_accesscount.egg-info/SOURCES.txt
flask_pluginkit_accesscount.egg-info/dependency_links.txt
flask_pluginkit_accesscount.egg-info/not-zip-safe
flask_pluginkit_accesscount.egg-info/requires.txt
flask_pluginkit_accesscount.egg-info/top_level.txt